sqlgbm/__init__.py
sqlgbm/core.py
sqlgbm-0.2.0.dist-info/METADATA
sqlgbm-0.2.0.dist-info/WHEEL
sqlgbm-0.2.0.dist-info/licenses/LICENSE
sqlgbm-0.2.0.dist-info/RECORD
