Metadata-Version: 2.4
Name: sqlgbm
Version: 0.2.0
Summary: Convert tree-based ML models to SQL queries
Project-URL: Homepage, https://github.com/mattismegevand/sqlgbm
Project-URL: Bug Tracker, https://github.com/mattismegevand/sqlgbm/issues
Author-email: Mattis Megevand <megevand.mattis@gmail.com>
License-File: LICENSE
Classifier: License :: OSI Approved :: MIT License
Classifier: Operating System :: OS Independent
Classifier: Programming Language :: Python :: 3
Requires-Python: >=3.7
Requires-Dist: pandas>=1.0.0
